pycharge/__init__.py
pycharge/charge.py
pycharge/potentials_and_fields.py
pycharge/py.typed
pycharge/simulate.py
pycharge/sources.py
pycharge/types.py
pycharge/functional/__init__.py
pycharge/functional/functional.py
pycharge-2.0.1.dist-info/METADATA
pycharge-2.0.1.dist-info/WHEEL
pycharge-2.0.1.dist-info/licenses/LICENSE
pycharge-2.0.1.dist-info/RECORD
