Metadata-Version: 2.4
Name: pycharge
Version: 2.0.1
Summary: Python library for differentiable electrodynamics simulations with jax.
Project-URL: Homepage, https://github.com/MatthewFilipovich/pycharge
Project-URL: Documentation, https://pycharge.readthedocs.io/
Project-URL: Tracker, https://github.com/MatthewFilipovich/pycharge/issues
Project-URL: Changelog, https://github.com/MatthewFilipovich/pycharge/releases
Author-email: Matthew Filipovich <matthew.filipovich@physics.ox.ac.uk>
License-Expression: MIT
License-File: LICENSE
Keywords: differentiable optics,electrodynamics,inverse design,jax,physics
Classifier: Intended Audience :: Education
Classifier: Intended Audience :: Science/Research
Classifier: License :: OSI Approved :: MIT License
Classifier: Operating System :: OS Independent
Classifier: Programming Language :: Python
Classifier: Programming Language :: Python :: 3
Classifier: Programming Language :: Python :: 3 :: Only
Classifier: Programming Language :: Python :: 3.10
Classifier: Programming Language :: Python :: 3.11
Classifier: Programming Language :: Python :: 3.12
Classifier: Programming Language :: Python :: 3.13
Classifier: Programming Language :: Python :: 3.14
Classifier: Topic :: Scientific/Engineering :: Physics
Requires-Python: >=3.10
Requires-Dist: jax
Requires-Dist: optimistix
Provides-Extra: dev
Requires-Dist: coverage; extra == 'dev'
Requires-Dist: pre-commit; extra == 'dev'
Requires-Dist: pyright; extra == 'dev'
Requires-Dist: pytest; extra == 'dev'
Requires-Dist: ruff; extra == 'dev'
Requires-Dist: scipy; extra == 'dev'
Provides-Extra: docs
Requires-Dist: matplotlib; extra == 'docs'
Requires-Dist: pydata-sphinx-theme; extra == 'docs'
Requires-Dist: sphinx-autoapi; extra == 'docs'
Requires-Dist: sphinx-copybutton; extra == 'docs'
Requires-Dist: sphinx-design; extra == 'docs'
Requires-Dist: sphinx-gallery; extra == 'docs'
